{"adult":false,"backdrop_path":"/o31kGDH9GbAZjVLwPYno8XvQGV2.jpg","budget":3000000,"genres":[{"id":28,"name":"Action"},{"id":53,"name":"Thriller"}],"homepage":"http://9bulletsmovie.com","id":777831,"imdb_id":"tt13680520","original_language":"en","original_title":"9 Bullets","overview":"A former burlesque dancer turned author discovers a second chance at life and redemption when she risks everything to rescue her young neighbor after he witnesses his parents’ murder. Now on the run from the local crime boss, who happens to be her longtime ex, she makes a desperate attempt to get the boy to safety.","popularity":25.147,"poster_path":"/cuFPxoFopAjFUz4oIMUzpzeTA8I.jpg","production_companies":[{"id":95837,"name":"Foresight Entertainment","origin_country":""},{"id":163946,"name":"Pop Films","origin_country":""},{"id":6353,"logo_path":"/7Fs0fMLWrPUaM3H0PK4hbnuEE1g.png","name":"Screen Media Films","origin_country":"US"}],"production_countries":[{"iso_3166_1":"US","name":"United States of America"}],"release_date":"2022-04-14","revenue":193908,"runtime":96,"spoken_languages":[{"english_name":"English","iso_639_1":"en","name":"English"}],"status":"Released","tagline":"One shot will change everything.","title":"9 Bullets","video":false,"vote_average":5.353,"vote_count":78,"casts":{"cast":[{"adult":false,"gender":1,"id":17286,"known_for_department":"Acting","name":"Lena Headey","original_name":"Lena Headey","popularity":30.652,"profile_path":"/i2fAeyUY42URnR0bR4wBYvAo2eB.jpg","cast_id":1,"character":"Gypsy Moon","credit_id":"5fde99ed764841003d6d8498","order":0},{"adult":false,"gender":2,"id":2940842,"known_for_department":"Acting","name":"Dean Scott Vazquez","original_name":"Dean Scott Vazquez","popularity":26.982,"profile_path":"/bo4Cmv8rXIYSskIbMFbrcIedFnG.jpg","cast_id":7,"character":"Sam","credit_id":"60a7abe6e16e5a003f889644","order":1},{"adult":false,"gender":2,"id":65731,"known_for_department":"Acting","name":"Sam Worthington","original_name":"Sam Worthington","popularity":53.937,"profile_path":"/mflBcox36s9ZPbsZPVOuhf6axaJ.jpg","cast_id":2,"character":"Jack","credit_id":"5fde99fad7107e003bc83d35","order":2},{"adult":false,"gender":1,"id":10767,"known_for_department":"Acting","name":"Barbara Hershey","original_name":"Barbara Hershey","popularity":10.142,"profile_path":"/6swwfge3HlvyBVRSNwroFtMcgNB.jpg","cast_id":4,"character":"Lacey","credit_id":"5fde9a4f3520e8003ef24cbf","order":3},{"adult":false,"gender":1,"id":1034453,"known_for_department":"Acting","name":"La La Anthony","original_name":"La La Anthony","popularity":7.159,"profile_path":"/34Ncdty8qOpdHSv75pI51GsitON.jpg","cast_id":11,"character":"Tasmin","credit_id":"60a7ac2585702e006eee117a","order":4},{"adult":false,"gender":2,"id":55086,"known_for_department":"Acting","name":"Cam Gigandet","original_name":"Cam Gigandet","popularity":16.354,"profile_path":"/kdSVRqCR0p8KZTvVkRccBLoim7L.jpg","cast_id":8,"character":"Tommy","credit_id":"60a7ac248dbc330041a19eee","order":5},{"adult":false,"gender":2,"id":212776,"known_for_department":"Acting","name":"Marc Menchaca","original_name":"Marc Menchaca","popularity":8.868,"profile_path":"/fL0LmdBwau30M4AFPVJrpLRXXsU.jpg","cast_id":9,"character":"Sheriff John Carter","credit_id":"60a7ac25142ef10040f10dbd","order":6},{"adult":false,"gender":1,"id":146004,"known_for_department":"Acting","name":"Marlene Forte","original_name":"Marlene Forte","popularity":4.509,"profile_path":"/qBhO3tT3VzF1bxUhw3ylmQsfTwP.jpg","cast_id":12,"character":"Grandma Lucy","credit_id":"60a7ac267dfda6005940d72a","order":7},{"adult":false,"gender":1,"id":2041321,"known_for_department":"Acting","name":"Stephanie Arcila","original_name":"Stephanie Arcila","popularity":16.527,"profile_path":"/oDUl6zoPz9v55KY0ZWXAlFsZY08.jpg","cast_id":13,"character":"Caroline","credit_id":"60a7ac268dbc330041a19ef1","order":8},{"adult":false,"gender":1,"id":1075505,"known_for_department":"Acting","name":"Emma Holzer","original_name":"Emma Holzer","popularity":3.076,"profile_path":"/dZIlQ9aRuLIwhQzKXH4iovkwILr.jpg","cast_id":14,"character":"Lisa","credit_id":"60a7ac268dbc330059955721","order":9},{"adult":false,"gender":2,"id":2170918,"known_for_department":"Acting","name":"Chris Mullinax","original_name":"Chris Mullinax","popularity":2.848,"profile_path":"/9BILCPkrZDuhLATdMhzVWKRe3yJ.jpg","cast_id":15,"character":"Mike","credit_id":"60a7ac27e16e5a003f8896be","order":10},{"adult":false,"gender":1,"id":94100,"known_for_department":"Acting","name":"Cornelia Guest","original_name":"Cornelia Guest","popularity":1.4,"profile_path":"/gcRtpJGz7G2I5lX1E2jkaCrlTss.jpg","cast_id":16,"character":"Jennifer","credit_id":"60a7ac27fac50200418f7459","order":11},{"adult":false,"gender":0,"id":2068213,"known_for_department":"Acting","name":"Zachary Mooren","original_name":"Zachary Mooren","popularity":0.6,"cast_id":17,"character":"Ralph Stein","credit_id":"60a7ac274b0c630057980d2a","order":12},{"adult":false,"gender":2,"id":84179,"known_for_department":"Acting","name":"Anthony Fitzgerald","original_name":"Anthony Fitzgerald","popularity":1.194,"profile_path":"/fqC6qj6plzpx763RnDEkQSnYyCG.jpg","cast_id":18,"character":"Mel","credit_id":"60a7ac284b0c63002a8b1c27","order":13},{"adult":false,"gender":2,"id":1584347,"known_for_department":"Acting","name":"Martin Sensmeier","original_name":"Martin Sensmeier","popularity":14.149,"profile_path":"/d25Mx8thmbgQWHR35S5s6MxjsCc.jpg","cast_id":10,"character":"Eddie","credit_id":"60a7ac259a64c100296582f7","order":14},{"adult":false,"gender":1,"id":2524667,"known_for_department":"Acting","name":"Claire Liz Phillips","original_name":"Claire Liz Phillips","popularity":0.6,"cast_id":19,"character":"Waitress (uncredited)","credit_id":"60a7ac28142ef1002785bb3c","order":15},{"adult":false,"gender":1,"id":13023,"known_for_department":"Acting","name":"Colleen Camp","original_name":"Colleen Camp","popularity":30.491,"profile_path":"/hNAIkUVtsQfpC95BDkXr1lmoI2F.jpg","cast_id":44,"character":"Drew","credit_id":"646a11f7a5046e00e5b6afd0","order":16},{"adult":false,"gender":1,"id":1883417,"known_for_department":"Production","name":"MJ Caballero","original_name":"MJ Caballero","popularity":0.6,"cast_id":45,"character":"Car Girl","credit_id":"646a1224006b0100e6b4ad5f","order":17},{"adult":false,"gender":0,"id":2032485,"known_for_department":"Acting","name":"Chelsea Davis","original_name":"Chelsea Davis","popularity":0.6,"cast_id":46,"character":"Waitress","credit_id":"646a124c2bcf6701389532f6","order":18}],"crew":[{"adult":false,"gender":1,"id":5914,"known_for_department":"Production","name":"Mary Vernieu","original_name":"Mary Vernieu","popularity":1.833,"credit_id":"646a118bd185720140316b49","department":"Production","job":"Casting"},{"adult":false,"gender":2,"id":64058,"known_for_department":"Production","name":"Cassian Elwes","original_name":"Cassian Elwes","popularity":1.532,"credit_id":"62a06483c8f8580065223a89","department":"Production","job":"Producer"},{"adult":false,"gender":2,"id":87625,"known_for_department":"Camera","name":"Byron Werner","original_name":"Byron Werner","popularity":1.4,"credit_id":"62a0649b1e922521e6838816","department":"Camera","job":"Director of Photography"},{"adult":false,"gender":2,"id":109422,"known_for_department":"Crew","name":"Rob Mars","original_name":"Rob Mars","popularity":2.424,"profile_path":"/hJFCXTiwTc4sh0c8eFTveBBEwYI.jpg","credit_id":"646a104d006b0101058a9745","department":"Crew","job":"Stunt Coordinator"},{"adult":false,"gender":0,"id":1034515,"known_for_department":"Sound","name":"Jeffery Alan Jones","original_name":"Jeffery Alan Jones","popularity":0.6,"credit_id":"63e058accd20460085b39a5e","department":"Sound","job":"Sound Designer"},{"adult":false,"gender":0,"id":1034515,"known_for_department":"Sound","name":"Jeffery Alan Jones","original_name":"Jeffery Alan Jones","popularity":0.6,"credit_id":"63e058b4373ac2007f020a37","department":"Sound","job":"Supervising Sound Editor"},{"adult":false,"gender":0,"id":1034515,"known_for_department":"Sound","name":"Jeffery Alan Jones","original_name":"Jeffery Alan Jones","popularity":0.6,"credit_id":"63e058a8ce5d82007ca4d40f","department":"Sound","job":"Sound Re-Recording Mixer"},{"adult":false,"gender":0,"id":1329111,"known_for_department":"Art","name":"Georgia Schwab","original_name":"Georgia Schwab","popularity":0.6,"credit_id":"646a11bca5046e01058bea3e","department":"Art","job":"Set Decoration"},{"adult":false,"gender":0,"id":1331166,"known_for_department":"Production","name":"Wendy Benge","original_name":"Wendy Benge","popularity":0.6,"credit_id":"62a06451c8f85800a5372174","department":"Production","job":"Producer"},{"adult":false,"gender":1,"id":1401855,"known_for_department":"Costume & Make-Up","name":"Lisa Norcia","original_name":"Lisa Norcia","popularity":0.6,"credit_id":"62a064c77d5db5086bf1b033","department":"Costume & Make-Up","job":"Costume Design"},{"adult":false,"gender":2,"id":1419137,"known_for_department":"Crew","name":"Brady Romberg","original_name":"Brady Romberg","popularity":0.98,"credit_id":"646a1036d1857201802d3f1c","department":"Crew","job":"Stunt Double"},{"adult":false,"gender":0,"id":1432050,"known_for_department":"Editing","name":"Halima K. Gilliam","original_name":"Halima K. Gilliam","popularity":0.6,"credit_id":"62a064af35d1bc0066102cec","department":"Editing","job":"Editor"},{"adult":false,"gender":1,"id":1463661,"known_for_department":"Crew","name":"Whitney Coleman","original_name":"Whitney Coleman","popularity":0.98,"profile_path":"/e6MyQLNmQUgIIoyJH5s4eGxVUF6.jpg","credit_id":"646a109a006b010147ea4461","department":"Crew","job":"Stunt Double"},{"adult":false,"gender":1,"id":1515545,"known_for_department":"Directing","name":"Gigi Gaston","original_name":"Gigi Gaston","popularity":0.732,"credit_id":"5fde9a641b157d003ec40251","department":"Directing","job":"Director"},{"adult":false,"gender":1,"id":1515545,"known_for_department":"Directing","name":"Gigi Gaston","original_name":"Gigi Gaston","popularity":0.732,"credit_id":"623f3636c50ad2008837c056","department":"Writing","job":"Writer"},{"adult":false,"gender":2,"id":1549741,"known_for_department":"Crew","name":"Marc Scizak","original_name":"Marc Scizak","popularity":0.774,"profile_path":"/6ubzEK40tiHwjOy9Y6lUGlfuFQ5.jpg","credit_id":"646a101e33a3760101fb3eed","department":"Crew","job":"Stunt Driver"},{"adult":false,"gender":0,"id":1620247,"known_for_department":"Editing","name":"Eve Doherty","original_name":"Eve Doherty","popularity":0.6,"credit_id":"62a064a51e922521e5f1be71","department":"Editing","job":"Editor"},{"adult":false,"gender":0,"id":1622277,"known_for_department":"Sound","name":"Hugo de Chaire","original_name":"Hugo de Chaire","popularity":0.6,"credit_id":"62a0648e7b7b4d00693a7e2d","department":"Sound","job":"Original Music Composer"},{"adult":false,"gender":0,"id":1622277,"known_for_department":"Sound","name":"Hugo de Chaire","original_name":"Hugo de Chaire","popularity":0.6,"credit_id":"646a10f52bcf6700e3bb1c2d","department":"Sound","job":"Music"},{"adult":false,"gender":2,"id":1685570,"known_for_department":"Production","name":"Bret Howe","original_name":"Bret Howe","popularity":1.4,"credit_id":"646a116533a3760175d33941","department":"Production","job":"Casting"},{"adult":false,"gender":0,"id":2616591,"known_for_department":"Art","name":"Réka Vivien Szabó","original_name":"Réka Vivien Szabó","popularity":0.6,"credit_id":"62a064bc53866e009c0c8307","department":"Art","job":"Production Design"},{"adult":false,"gender":0,"id":2743760,"known_for_department":"Production","name":"Benjamin Bermudez","original_name":"Benjamin Bermudez","popularity":0.6,"credit_id":"646a1004006b0100e6b4ac81","department":"Production","job":"Casting Assistant"},{"adult":false,"gender":0,"id":3580872,"known_for_department":"Production","name":"Howard C. Deshong","original_name":"Howard C. Deshong","popularity":0.6,"credit_id":"62a064675507e973ae52679d","department":"Production","job":"Producer"},{"adult":false,"gender":0,"id":4073182,"known_for_department":"Crew","name":"Zack Kraschinsky","original_name":"Zack Kraschinsky","popularity":0.6,"credit_id":"646a10832bcf670138953236","department":"Crew","job":"Stunt Double"},{"adult":false,"gender":0,"id":4073189,"known_for_department":"Art","name":"Laura Voglesong","original_name":"Laura Voglesong","popularity":0.6,"credit_id":"646a11a633a3760175d33967","department":"Art","job":"Art Direction"}]},"releases":{"countries":[{"certification":"","iso_3166_1":"US","primary":false,"release_date":"2022-04-22T00:00:00.0000000Z"},{"certification":"16+","iso_3166_1":"RU","primary":false,"release_date":"2022-04-14T00:00:00.0000000Z"},{"certification":"12","iso_3166_1":"FR","primary":false,"release_date":"2022-04-15T00:00:00.0000000Z"},{"certification":"MA15+","iso_3166_1":"AU","primary":false,"release_date":"2022-06-23T00:00:00.0000000Z"},{"certification":"","iso_3166_1":"US","primary":false,"release_date":"2022-04-22T00:00:00.0000000Z"},{"certification":"15","iso_3166_1":"GB","primary":false,"release_date":"2022-06-06T00:00:00.0000000Z"},{"certification":"16","iso_3166_1":"NZ","primary":false,"release_date":"2022-07-01T00:00:00.0000000Z"},{"certification":"16","iso_3166_1":"BR","primary":false,"release_date":"2022-06-22T00:00:00.0000000Z"},{"certification":"16","iso_3166_1":"DE","primary":false,"release_date":"2022-08-19T00:00:00.0000000Z"},{"certification":"16","iso_3166_1":"DE","primary":false,"release_date":"2022-08-26T00:00:00.0000000Z"}]},"images":{"backdrops":[{"aspect_ratio":1.778,"file_path":"/o31kGDH9GbAZjVLwPYno8XvQGV2.jpg","height":2160,"vote_average":5.384,"vote_count":2,"width":3840},{"aspect_ratio":1.778,"file_path":"/vDvtCVvzOdxjBctSH3fyu1wCkuX.jpg","height":2160,"vote_average":5.312,"vote_count":1,"width":3840},{"aspect_ratio":1.778,"file_path":"/vmcqMsRCaJzPe7dWoDXo0CyLZOB.jpg","height":1080,"iso_639_1":"en","vote_average":5.312,"vote_count":1,"width":1920},{"aspect_ratio":1.778,"file_path":"/oKCFaXAFGINjJs0uEVOvQhJPXSQ.jpg","height":720,"vote_average":5.246,"vote_count":2,"width":1280},{"aspect_ratio":1.778,"file_path":"/d31linHLUe0mxX2mUulPsS0CDKQ.jpg","height":720,"iso_639_1":"en","vote_average":0,"vote_count":0,"width":1280},{"aspect_ratio":1.777,"file_path":"/rWzYUJ7IFZbIv5o9AuRgRaiO0Bu.jpg","height":1077,"vote_average":0,"vote_count":0,"width":1914},{"aspect_ratio":1.778,"file_path":"/ztakIMTyssLn0Zytgvinm8Zzhpu.jpg","height":2160,"vote_average":0,"vote_count":0,"width":3840},{"aspect_ratio":1.778,"file_path":"/kVME2VJul3mcJEkA7otwFkKliJQ.jpg","height":1080,"vote_average":0,"vote_count":0,"width":1920},{"aspect_ratio":1.778,"file_path":"/nf0DKWf24TaxkDNjpCtqQ7Ylazj.jpg","height":2160,"vote_average":0,"vote_count":0,"width":3840},{"aspect_ratio":1.778,"file_path":"/bfgyqtyGWc3DKvWXvpx0Arv2UMS.jpg","height":1080,"vote_average":0,"vote_count":0,"width":1920},{"aspect_ratio":1.778,"file_path":"/si0t3nOxDYlEJnCtdF7zT8b7qpR.jpg","height":1080,"iso_639_1":"en","vote_average":0,"vote_count":0,"width":1920},{"aspect_ratio":1.778,"file_path":"/ejX8KOnyTaLpydtV2rQeyD5YAjb.jpg","height":1080,"vote_average":0,"vote_count":0,"width":1920},{"aspect_ratio":1.778,"file_path":"/mfFuFQo0Mk0n7WlH0CBqiTXPGyL.jpg","height":1080,"vote_average":0,"vote_count":0,"width":1920},{"aspect_ratio":1.778,"file_path":"/9CV0D09jfO5WhPrKnZi55Uw8HLQ.jpg","height":1080,"vote_average":0,"vote_count":0,"width":1920}],"posters":[{"aspect_ratio":0.667,"file_path":"/cuFPxoFopAjFUz4oIMUzpzeTA8I.jpg","height":3000,"iso_639_1":"en","vote_average":5.384,"vote_count":2,"width":2000},{"aspect_ratio":0.667,"file_path":"/jXicR85hb2HbeszMCY61uu0sBxO.jpg","height":3000,"iso_639_1":"en","vote_average":5.312,"vote_count":1,"width":2000},{"aspect_ratio":0.666,"file_path":"/4WjW6H3s4yS5QriZ5T5c9zvYGaP.jpg","height":1763,"iso_639_1":"en","vote_average":5.246,"vote_count":2,"width":1175},{"aspect_ratio":0.667,"file_path":"/1PZykED7EWMtQsFJYKougTsrnyu.jpg","height":1185,"iso_639_1":"en","vote_average":5.172,"vote_count":1,"width":790},{"aspect_ratio":0.667,"file_path":"/eTfDexOEyfK3ZoD6XEjLRFb1S2Q.jpg","height":1599,"iso_639_1":"en","vote_average":5.172,"vote_count":1,"width":1066},{"aspect_ratio":0.667,"file_path":"/8h8R2D6AVTZCCA6NIvioObkhXsb.jpg","height":1599,"iso_639_1":"en","vote_average":0,"vote_count":0,"width":1066},{"aspect_ratio":0.667,"file_path":"/nwnmRV6HJwpwpUoT4VztbMXrMRR.jpg","height":3000,"vote_average":0,"vote_count":0,"width":2000}],"logos":[{"aspect_ratio":2.709,"file_path":"/hTGb7zHmM5d4ZbCuf5BATjQJclF.png","height":289,"iso_639_1":"en","vote_average":0,"vote_count":0,"width":783},{"aspect_ratio":2.709,"file_path":"/kpAhzusnuWhB8l8S1wJxwYWL6xV.png","height":289,"iso_639_1":"en","vote_average":0,"vote_count":0,"width":783}]},"keywords":{"keywords":[{"id":733,"name":"dancer"},{"id":5982,"name":"ex husband"},{"id":6203,"name":"loss"},{"id":9730,"name":"crime boss"},{"id":9826,"name":"murder"},{"id":10084,"name":"rescue"},{"id":10226,"name":"neighbor"},{"id":10562,"name":"on the run"},{"id":10818,"name":"author"},{"id":11107,"name":"rescue mission"},{"id":13028,"name":"writer"},{"id":18035,"name":"family"},{"id":34004,"name":"second chance"},{"id":163070,"name":"burlesque"}]},"trailers":{"quicktime":[],"youtube":[{"name":"Official Trailer","size":"HD","source":"_KwZ1tuibHw","type":"Trailer"},{"name":"UK Trailer","size":"HD","source":"FyZcUWLvyos","type":"Trailer"},{"name":"9 Bullets - \"Graveyard\" Clip","size":"HD","source":"UG1hzxrCntI","type":"Clip"}]}}